aiida_pytest/__init__.py
aiida_pytest/_code.py
aiida_pytest/_compare.py
aiida_pytest/_computer.py
aiida_pytest/_configure.py
aiida_pytest/_entrypoints.py
aiida_pytest/_process.py
aiida_pytest/_pseudo_family.py
aiida_pytest/_sample.py
aiida_pytest/contextmanagers.py
aiida_pytest-0.1.0a8.dist-info/LICENSE.txt
aiida_pytest-0.1.0a8.dist-info/METADATA
aiida_pytest-0.1.0a8.dist-info/WHEEL
aiida_pytest-0.1.0a8.dist-info/top_level.txt
aiida_pytest-0.1.0a8.dist-info/RECORD
