Metadata-Version: 2.1
Name: aiida-pytest
Version: 0.1.0a8
Summary: A module to simplify using pytest for AiiDA plugins.
Home-page: UNKNOWN
Author: Dominik Gresch
Author-email: greschd@gmx.ch
License: Apache 2.0
Keywords: pytest aiida workflows
Platform: UNKNOWN
Classifier: Development Status :: 3 - Alpha
Classifier: Environment :: Plugins
Classifier: Intended Audience :: Science/Research
Classifier: License :: OSI Approved :: Apache Software License
Classifier: Programming Language :: Python :: 3
Classifier: Programming Language :: Python :: 3.6
Classifier: Programming Language :: Python :: 3.7
Classifier: Programming Language :: Python :: 3.8
Classifier: Topic :: Scientific/Engineering :: Physics
Classifier: Topic :: Software Development :: Testing
Classifier: Framework :: Pytest
Classifier: Framework :: AiiDA
Requires-Python: >=3.6
Requires-Dist: aiida-core (<2.0.0,>=1.0.0)
Requires-Dist: pytest
Requires-Dist: pyyaml
Requires-Dist: pgtest (>=1.1)
